Workbook

Sheet master
A1: Account | B1: bbgid | C1: rawTicker | D1: name | E1: lei | F1: title | G1: cusip | H1: isin | I1: ticker | J1: invCountry | K1: assetCat | L1: issuerCat | M1: derivCat | N1: counterpartyName | O1: counterpartyLei | P1: putOrCall | Q1: writtenOrPur | R1: exercisePrice | S1: exercisePriceCurCd | T1: expDt | U1: delta | V1: refInstType | W1: refIndexName | X1: refIndexIdentifier | Y1: swapFlag | Z1: terminationDt | AA1: notionalAmt | AB1: swapCurCd | AC1: unrealizedAppr | AD1: valUSD | AE1: pctVal | AF1: recFixedOrFloating | AG1: recDesc | AH1: pmntFixedOrFloating | AI1: pmntFloatingRtIndex | AJ1: pmntFloatingRtSpread | AK1: pmntPmntAmt | AL1: pmntCurCdLeg | AM1: pmntRateTenor | AN1: pmntRateUnit | AO1: refIssuerName | AP1: refIssueTitle | AQ1: refCusip | AR1: refIsin | AS1: refTicker | AT1: maturityDt | AU1: couponKind | AV1: annualizedRt | AW1: isDefault | AX1: areIntrstPmntsInArrs | AY1: isPaidKind
A2: GPTZ | C2: Cash&Other | G2: =custodian!D2
A3: ACLZ | B3: 054540208 Equity | C3: 054540208-TRS-12/01/27-L-CANT | D3: N/A | E3: N/A | F3: AXCELIS TECHNOLOGIES, INC.-SWAP-CANT-L | G3: =custodian!D3 | I3: 054540208-TRS-12/01/27-L-CANT | J3: US | K3: DE | L3: OTHER | M3: SWP | V3: otherRefInst | Y3: Y | Z3: 2027-12-01 | AA3: 485785.16 | AB3: USD | AC3: -6321.11 | AD3: -6321.11 | AE3: -2.59 | AH3: Floating | AK3: 485785.16 | AL3: USD | AO3: =BDP($B3,"ISSUER") | AP3: =BDP($B3,"NAME") | AQ3: 054540208 | AR3: =BDP($B3,"ID_ISIN") | AS3: =BDP($B3,"TICKER")
A4: ACLZ | B4: FGXXX US Equity | C4: FGXXX | D4: First American Government Obli | E4: =BDP($B4,"LEGAL_ENTITY_IDENTIFIER") | F4: First American Government Obligations Fund | G4: =custodian!D4 | H4: =BDP($B4,"ID_ISIN") | I4: FGXXX | J4: =BDP($B4,"CNTRY_OF_DOMICILE") | K4: STIV | L4: RF
A5: ACLZ | C5: Cash&Other | G5: =custodian!D5
A6: ACMM | B6: 00108J109 Equity | C6: 00108J109-TRS-07/26/27-L-MREX | D6: N/A | E6: N/A | F6: ACM RESEARCH, INC.-SWAP-MREX-L | G6: =custodian!D6 | I6: 00108J109-TRS-07/26/27-L-MREX | J6: US | K6: DE | L6: OTHER | M6: SWP | V6: otherRefInst | Y6: Y | Z6: 2027-07-26 | AA6: 519176.00 | AB6: USD | AC6: 12399.29 | AD6: 12399.29 | AE6: 4.72 | AH6: Floating | AK6: 519176.00 | AL6: USD | AO6: =BDP($B6,"ISSUER") | AP6: =BDP($B6,"NAME") | AQ6: 00108J109 | AR6: =BDP($B6,"ID_ISIN") | AS6: =BDP($B6,"TICKER")
A7: ACMM | B7: FGXXX US Equity | C7: FGXXX | D7: First American Government Obli | E7: =BDP($B7,"LEGAL_ENTITY_IDENTIFIER") | F7: First American Government Obligations Fund | G7: =custodian!D7 | H7: =BDP($B7,"ID_ISIN") | I7: FGXXX | J7: =BDP($B7,"CNTRY_OF_DOMICILE") | K7: STIV | L7: RF
A8: ACMM | C8: Cash&Other | G8: =custodian!D8
A9: AV | B9: AAL US Equity | C9: AAL | D9: American Airlines Group Inc | E9: =BDP($B9,"LEGAL_ENTITY_IDENTIFIER") | F9: American Airlines Group Inc | G9: =custodian!D9 | H9: =BDP($B9,"ID_ISIN") | I9: AAL | J9: =BDP($B9,"CNTRY_OF_DOMICILE") | K9: EC | L9: CORP
A10: AV | B10: AER US Equity | C10: AER | D10: AerCap Holdings NV | E10: =BDP($B10,"LEGAL_ENTITY_IDENTIFIER") | F10: AerCap Holdings NV | G10: =custodian!D10 | H10: =BDP($B10,"ID_ISIN") | I10: AER | J10: =BDP($B10,"CNTRY_OF_DOMICILE") | K10: EC | L10: CORP
A11: AV | B11: AIR US Equity | C11: AIR | D11: AAR Corp | E11: =BDP($B11,"LEGAL_ENTITY_IDENTIFIER") | F11: AAR Corp | G11: =custodian!D11 | H11: =BDP($B11,"ID_ISIN") | I11: AIR | J11: =BDP($B11,"CNTRY_OF_DOMICILE") | K11: EC | L11: CORP
A12: AV | B12: ALGT US Equity | C12: ALGT | D12: Allegiant Travel Co | E12: =BDP($B12,"LEGAL_ENTITY_IDENTIFIER") | F12: Allegiant Travel Co | G12: =custodian!D12 | H12: =BDP($B12,"ID_ISIN") | I12: ALGT | J12: =BDP($B12,"CNTRY_OF_DOMICILE") | K12: EC | L12: CORP
A13: AV | B13: ALK US Equity | C13: ALK | D13: Alaska Air Group Inc | E13: =BDP($B13,"LEGAL_ENTITY_IDENTIFIER") | F13: Alaska Air Group Inc | G13: =custodian!D13 | H13: =BDP($B13,"ID_ISIN") | I13: ALK | J13: =BDP($B13,"CNTRY_OF_DOMICILE") | K13: EC | L13: CORP
A14: AV | B14: ASR US Equity | C14: ASR | D14: Grupo Aeroportuario del Surest | E14: =BDP($B14,"LEGAL_ENTITY_IDENTIFIER") | F14: Grupo Aeroportuario del Sureste SAB de CV | G14: =custodian!D14 | H14: =BDP($B14,"ID_ISIN") | I14: ASR | J14: =BDP($B14,"CNTRY_OF_DOMICILE") | K14: EC | L14: CORP
A15: AV | B15: ATI US Equity | C15: ATI | D15: ATI Inc | E15: =BDP($B15,"LEGAL_ENTITY_IDENTIFIER") | F15: ATI Inc | G15: =custodian!D15 | H15: =BDP($B15,"ID_ISIN") | I15: ATI | J15: =BDP($B15,"CNTRY_OF_DOMICILE") | K15: EC | L15: CORP
A16: AV | B16: BA US Equity | C16: BA | D16: Boeing Co/The | E16: =BDP($B16,"LEGAL_ENTITY_IDENTIFIER") | F16: Boeing Co/The | G16: =custodian!D16 | H16: =BDP($B16,"ID_ISIN") | I16: BA | J16: =BDP($B16,"CNTRY_OF_DOMICILE") | K16: EC | L16: CORP
A17: AV | B17: CAE US Equity | C17: CAE | D17: CAE Inc | E17: =BDP($B17,"LEGAL_ENTITY_IDENTIFIER") | F17: CAE Inc | G17: =custodian!D17 | H17: =BDP($B17,"ID_ISIN") | I17: CAE | J17: =BDP($B17,"CNTRY_OF_DOMICILE") | K17: EC | L17: CORP
A18: AV | B18: CPA US Equity | C18: CPA | D18: Copa Holdings SA | E18: =BDP($B18,"LEGAL_ENTITY_IDENTIFIER") | F18: Copa Holdings SA | G18: =custodian!D18 | H18: =BDP($B18,"ID_ISIN") | I18: CPA | J18: =BDP($B18,"CNTRY_OF_DOMICILE") | K18: EC | L18: CORP
A19: AV | B19: CRS US Equity | C19: CRS | D19: Carpenter Technology Corp | E19: =BDP($B19,"LEGAL_ENTITY_IDENTIFIER") | F19: Carpenter Technology Corp | G19: =custodian!D19 | H19: =BDP($B19,"ID_ISIN") | I19: CRS | J19: =BDP($B19,"CNTRY_OF_DOMICILE") | K19: EC | L19: CORP
A20: AV | B20: DAL US Equity | C20: DAL | D20: Delta Air Lines Inc | E20: =BDP($B20,"LEGAL_ENTITY_IDENTIFIER") | F20: Delta Air Lines Inc | G20: =custodian!D20 | H20: =BDP($B20,"ID_ISIN") | I20: DAL | J20: =BDP($B20,"CNTRY_OF_DOMICILE") | K20: EC | L20: CORP
... A48: AV | B48: WWD US Equity | C48: WWD | D48: Woodward Inc | E48: =BDP($B48,"LEGAL_ENTITY_IDENTIFIER") | F48: Woodward Inc | G48: =custodian!D48 | H48: =BDP($B48,"ID_ISIN") | I48: WWD | J48: =BDP($B48,"CNTRY_OF_DOMICILE") | K48: EC | L48: CORP
A49: AV | C49: Cash&Other | G49: =custodian!D49
A50: BAY | B50: AAPL US Equity | C50: AAPL | D50: Apple Inc | E50: =BDP($B50,"LEGAL_ENTITY_IDENTIFIER") | F50: Apple Inc | G50: =custodian!D50 | H50: =BDP($B50,"ID_ISIN") | I50: AAPL | J50: =BDP($B50,"CNTRY_OF_DOMICILE") | K50: EC | L50: CORP
A51: BAY | B51: ABNB US Equity | C51: ABNB | D51: Airbnb Inc | E51: =BDP($B51,"LEGAL_ENTITY_IDENTIFIER") | F51: Airbnb Inc | G51: =custodian!D51 | H51: =BDP($B51,"ID_ISIN") | I51: ABNB | J51: =BDP($B51,"CNTRY_OF_DOMICILE") | K51: EC | L51: CORP
A52: BAY | B52: ADBE US Equity | C52: ADBE | D52: Adobe Inc | E52: =BDP($B52,"LEGAL_ENTITY_IDENTIFIER") | F52: Adobe Inc | G52: =custodian!D52 | H52: =BDP($B52,"ID_ISIN") | I52: ADBE | J52: =BDP($B52,"CNTRY_OF_DOMICILE") | K52: EC | L52: CORP
A53: BAY | B53: ADSK US Equity | C53: ADSK | D53: Autodesk Inc | E53: =BDP($B53,"LEGAL_ENTITY_IDENTIFIER") | F53: Autodesk Inc | G53: =custodian!D53 | H53: =BDP($B53,"ID_ISIN") | I53: ADSK | J53: =BDP($B53,"CNTRY_OF_DOMICILE") | K53: EC | L53: CORP
A54: BAY | B54: AFRM US Equity | C54: AFRM | D54: Affirm Holdings Inc | E54: =BDP($B54,"LEGAL_ENTITY_IDENTIFIER") | F54: Affirm Holdings Inc | G54: =custodian!D54 | H54: =BDP($B54,"ID_ISIN") | I54: AFRM | J54: =BDP($B54,"CNTRY_OF_DOMICILE") | K54: EC | L54: CORP
A55: BAY | B55: ALAB US Equity | C55: ALAB | D55: Astera Labs Inc | E55: =BDP($B55,"LEGAL_ENTITY_IDENTIFIER") | F55: Astera Labs Inc | G55: =custodian!D55 | H55: =BDP($B55,"ID_ISIN") | I55: ALAB | J55: =BDP($B55,"CNTRY_OF_DOMICILE") | K55: EC | L55: CORP
A56: BAY | B56: AMAT US Equity | C56: AMAT | D56: Applied Materials Inc | E56: =BDP($B56,"LEGAL_ENTITY_IDENTIFIER") | F56: Applied Materials Inc | G56: =custodian!D56 | H56: =BDP($B56,"ID_ISIN") | I56: AMAT | J56: =BDP($B56,"CNTRY_OF_DOMICILE") | K56: EC | L56: CORP
A57: BAY | B57: AMD US Equity | C57: AMD | D57: Advanced Micro Devices Inc | E57: =BDP($B57,"LEGAL_ENTITY_IDENTIFIER") | F57: Advanced Micro Devices Inc | G57: =custodian!D57 | H57: =BDP($B57,"ID_ISIN") | I57: AMD | J57: =BDP($B57,"CNTRY_OF_DOMICILE") | K57: EC | L57: CORP
A58: BAY | B58: APP US Equity | C58: APP | D58: AppLovin Corp | E58: =BDP($B58,"LEGAL_ENTITY_IDENTIFIER") | F58: AppLovin Corp | G58: =custodian!D58 | H58: =BDP($B58,"ID_ISIN") | I58: APP | J58: =BDP($B58,"CNTRY_OF_DOMICILE") | K58: EC | L58: CORP
A59: BAY | B59: AVGO US Equity | C59: AVGO | D59: Broadcom Inc | E59: =BDP($B59,"LEGAL_ENTITY_IDENTIFIER") | F59: Broadcom Inc | G59: =custodian!D59 | H59: =BDP($B59,"ID_ISIN") | I59: AVGO | J59: =BDP($B59,"CNTRY_OF_DOMICILE") | K59: EC | L59: CORP
A60: BAY | B60: BBIO US Equity | C60: BBIO | D60: Bridgebio Pharma Inc | E60: =BDP($B60,"LEGAL_ENTITY_IDENTIFIER") | F60: Bridgebio Pharma Inc | G60: =custodian!D60 | H60: =BDP($B60,"ID_ISIN") | I60: BBIO | J60: =BDP($B60,"CNTRY_OF_DOMICILE") | K60: EC | L60: CORP
A61: BAY | B61: BE US Equity | C61: BE | D61: Bloom Energy Corp | E61: =BDP($B61,"LEGAL_ENTITY_IDENTIFIER") | F61: Bloom Energy Corp | G61: =custodian!D61 | H61: =BDP($B61,"ID_ISIN") | I61: BE | J61: =BDP($B61,"CNTRY_OF_DOMICILE") | K61: EC | L61: CORP
... A109: BAY | B109: ZS US Equity | C109: ZS | D109: Zscaler Inc | E109: =BDP($B109,"LEGAL_ENTITY_IDENTIFIER") | F109: Zscaler Inc | G109: =custodian!D109 | H109: =BDP($B109,"ID_ISIN") | I109: ZS | J109: =BDP($B109,"CNTRY_OF_DOMICILE") | K109: EC | L109: CORP
A110: BAY | C110: Cash&Other | G110: =custodian!D110
A111: BLCK | B111: APLD US Equity | C111: APLD | D111: Applied Digital Corp | E111: =BDP($B111,"LEGAL_ENTITY_IDENTIFIER") | F111: Applied Digital Corp | G111: =custodian!D111 | H111: =BDP($B111,"ID_ISIN") | I111: APLD | J111: =BDP($B111,"CNTRY_OF_DOMICILE") | K111: EC | L111: CORP
A112: BLCK | B112: BKKT US Equity | C112: BKKT | D112: Bakkt Inc | E112: =BDP($B112,"LEGAL_ENTITY_IDENTIFIER") | F112: Bakkt Inc | G112: =custodian!D112 | H112: =BDP($B112,"ID_ISIN") | I112: BKKT | J112: =BDP($B112,"CNTRY_OF_DOMICILE") | K112: EC | L112: CORP
A113: BLCK | B113: BLSH US Equity | C113: BLSH | D113: Bullish | E113: =BDP($B113,"LEGAL_ENTITY_IDENTIFIER") | F113: Bullish | G113: =custodian!D113 | H113: =BDP($B113,"ID_ISIN") | I113: BLSH | J113: =BDP($B113,"CNTRY_OF_DOMICILE") | K113: EC | L113: CORP
A114: BLCK | B114: BMNR US Equity | C114: BMNR | D114: BitMine Immersion Technologies | E114: =BDP($B114,"LEGAL_ENTITY_IDENTIFIER") | F114: BitMine Immersion Technologies Inc | G114: =custodian!D114 | H114: =BDP($B114,"ID_ISIN") | I114: BMNR | J114: =BDP($B114,"CNTRY_OF_DOMICILE") | K114: EC | L114: CORP
A115: BLCK | B115: BTBT US Equity | C115: BTBT | D115: Bit Digital Inc | E115: =BDP($B115,"LEGAL_ENTITY_IDENTIFIER") | F115: Bit Digital Inc | G115: =custodian!D115 | H115: =BDP($B115,"ID_ISIN") | I115: BTBT | J115: =BDP($B115,"CNTRY_OF_DOMICILE") | K115: EC | L115: CORP
A116: BLCK | B116: BTDR US Equity | C116: BTDR | D116: Bitdeer Technologies Group | E116: =BDP($B116,"LEGAL_ENTITY_IDENTIFIER") | F116: Bitdeer Technologies Group | G116: =custodian!D116 | H116: =BDP($B116,"ID_ISIN") | I116: BTDR | J116: =BDP($B116,"CNTRY_OF_DOMICILE") | K116: EC | L116: CORP
A117: BLCK | B117: BTGO US Equity | C117: BTGO | D117: Bitgo Holdings Inc | E117: =BDP($B117,"LEGAL_ENTITY_IDENTIFIER") | F117: Bitgo Holdings Inc | G117: =custodian!D117 | H117: =BDP($B117,"ID_ISIN") | I117: BTGO | J117: =BDP($B117,"CNTRY_OF_DOMICILE") | K117: EC | L117: CORP
A118: BLCK | B118: CANG US Equity | C118: CANG | D118: Cango Inc/KY | E118: =BDP($B118,"LEGAL_ENTITY_IDENTIFIER") | F118: Cango Inc/KY | G118: =custodian!D118 | H118: =BDP($B118,"ID_ISIN") | I118: CANG | J118: =BDP($B118,"CNTRY_OF_DOMICILE") | K118: EC | L118: CORP
A119: BLCK | B119: CBOE US Equity | C119: CBOE | D119: Cboe Global Markets Inc | E119: =BDP($B119,"LEGAL_ENTITY_IDENTIFIER") | F119: Cboe Global Markets Inc | G119: =custodian!D119 | H119: =BDP($B119,"ID_ISIN") | I119: CBOE | J119: =BDP($B119,"CNTRY_OF_DOMICILE") | K119: EC | L119: CORP
A120: BLCK | B120: CIFR US Equity | C120: CIFR | D120: Cipher Digital Inc | E120: =BDP($B120,"LEGAL_ENTITY_IDENTIFIER") | F120: Cipher Digital Inc | G120: =custodian!D120 | H120: =BDP($B120,"ID_ISIN") | I120: CIFR | J120: =BDP($B120,"CNTRY_OF_DOMICILE") | K120: EC | L120: CORP
A121: BLCK | B121: CLSK US Equity | C121: CLSK | D121: Cleanspark Inc | E121: =BDP($B121,"LEGAL_ENTITY_IDENTIFIER") | F121: Cleanspark Inc | G121: =custodian!D121 | H121: =BDP($B121,"ID_ISIN") | I121: CLSK | J121: =BDP($B121,"CNTRY_OF_DOMICILE") | K121: EC | L121: CORP
A122: BLCK | B122: CME US Equity | C122: CME | D122: CME Group Inc | E122: =BDP($B122,"LEGAL_ENTITY_IDENTIFIER") | F122: CME Group Inc | G122: =custodian!D122 | H122: =BDP($B122,"ID_ISIN") | I122: CME | J122: =BDP($B122,"CNTRY_OF_DOMICILE") | K122: EC | L122: CORP
... A144: BLCK | B144: XYZ US Equity | C144: XYZ | D144: Block Inc | E144: =BDP($B144,"LEGAL_ENTITY_IDENTIFIER") | F144: Block Inc | G144: =custodian!D144 | H144: =BDP($B144,"ID_ISIN") | I144: XYZ | J144: =BDP($B144,"CNTRY_OF_DOMICILE") | K144: EC | L144: CORP
A145: BLCK | C145: Cash&Other | G145: =custodian!D145
A146: BREW | B146: BRCC US Equity | C146: BRCC | D146: BRC Inc | E146: =BDP($B146,"LEGAL_ENTITY_IDENTIFIER") | F146: BRC Inc | G146: =custodian!D146 | H146: =BDP($B146,"ID_ISIN") | I146: BRCC | J146: =BDP($B146,"CNTRY_OF_DOMICILE") | K146: EC | L146: CORP
A147: BREW | B147: BROS US Equity | C147: BROS | D147: Dutch Bros Inc | E147: =BDP($B147,"LEGAL_ENTITY_IDENTIFIER") | F147: Dutch Bros Inc | G147: =custodian!D147 | H147: =BDP($B147,"ID_ISIN") | I147: BROS | J147: =BDP($B147,"CNTRY_OF_DOMICILE") | K147: EC | L147: CORP
A148: BREW | B148: CELH US Equity | C148: CELH | D148: Celsius Holdings Inc | E148: =BDP($B148,"LEGAL_ENTITY_IDENTIFIER") | F148: Celsius Holdings Inc | G148: =custodian!D148 | H148: =BDP($B148,"ID_ISIN") | I148: CELH | J148: =BDP($B148,"CNTRY_OF_DOMICILE") | K148: EC | L148: CORP
A149: BREW | B149: DNUT US Equity | C149: DNUT | D149: Krispy Kreme Inc | E149: =BDP($B149,"LEGAL_ENTITY_IDENTIFIER") | F149: Krispy Kreme Inc | G149: =custodian!D149 | H149: =BDP($B149,"ID_ISIN") | I149: DNUT | J149: =BDP($B149,"CNTRY_OF_DOMICILE") | K149: EC | L149: CORP
A150: BREW | B150: FGXXX US Equity | C150: FGXXX | D150: First American Government Obli | E150: =BDP($B150,"LEGAL_ENTITY_IDENTIFIER") | F150: First American Government Obligations Fund | G150: =custodian!D150 | H150: =BDP($B150,"ID_ISIN") | I150: FGXXX | J150: =BDP($B150,"CNTRY_OF_DOMICILE") | K150: STIV | L150: RF
A151: BREW | B151: IFF US Equity | C151: IFF | D151: International Flavors & Fragra | E151: =BDP($B151,"LEGAL_ENTITY_IDENTIFIER") | F151: International Flavors & Fragrances Inc | G151: =custodian!D151 | H151: =BDP($B151,"ID_ISIN") | I151: IFF | J151: =BDP($B151,"CNTRY_OF_DOMICILE") | K151: EC | L151: CORP
A152: BREW | B152: INGR US Equity | C152: INGR | D152: Ingredion Inc | E152: =BDP($B152,"LEGAL_ENTITY_IDENTIFIER") | F152: Ingredion Inc | G152: =custodian!D152 | H152: =BDP($B152,"ID_ISIN") | I152: INGR | J152: =BDP($B152,"CNTRY_OF_DOMICILE") | K152: EC | L152: CORP
A153: BREW | B153: KDP US Equity | C153: KDP | D153: Keurig Dr Pepper Inc | E153: =BDP($B153,"LEGAL_ENTITY_IDENTIFIER") | F153: Keurig Dr Pepper Inc | G153: =custodian!D153 | H153: =BDP($B153,"ID_ISIN") | I153: KDP | J153: =BDP($B153,"CNTRY_OF_DOMICILE") | K153: EC | L153: CORP
A154: BREW | B154: KO US Equity | C154: KO | D154: Coca-Cola Co/The | E154: =BDP($B154,"LEGAL_ENTITY_IDENTIFIER") | F154: Coca-Cola Co/The | G154: =custodian!D154 | H154: =BDP($B154,"ID_ISIN") | I154: KO | J154: =BDP($B154,"CNTRY_OF_DOMICILE") | K154: EC | L154: CORP
A155: BREW | B155: MNST US Equity | C155: MNST | D155: Monster Beverage Corp | E155: =BDP($B155,"LEGAL_ENTITY_IDENTIFIER") | F155: Monster Beverage Corp | G155: =custodian!D155 | H155: =BDP($B155,"ID_ISIN") | I155: MNST | J155: =BDP($B155,"CNTRY_OF_DOMICILE") | K155: EC | L155: CORP
A156: BREW | B156: PEP US Equity | C156: PEP | D156: PepsiCo Inc | E156: =BDP($B156,"LEGAL_ENTITY_IDENTIFIER") | F156: PepsiCo Inc | G156: =custodian!D156 | H156: =BDP($B156,"ID_ISIN") | I156: PEP | J156: =BDP($B156,"CNTRY_OF_DOMICILE") | K156: EC | L156: CORP
A157: BREW | B157: QSR US Equity | C157: QSR | D157: Restaurant Brands Internationa | E157: =BDP($B157,"LEGAL_ENTITY_IDENTIFIER") | F157: Restaurant Brands International Inc | G157: =custodian!D157 | H157: =BDP($B157,"ID_ISIN") | I157: QSR | J157: =BDP($B157,"CNTRY_OF_DOMICILE") | K157: EC | L157: CORP
... A162: BREW | B162: ZVIA US Equity | C162: ZVIA | D162: Zevia PBC | E162: =BDP($B162,"LEGAL_ENTITY_IDENTIFIER") | F162: Zevia PBC | G162: =custodian!D162 | H162: =BDP($B162,"ID_ISIN") | I162: ZVIA | J162: =BDP($B162,"CNTRY_OF_DOMICILE") | K162: EC | L162: CORP
A163: BREW | C163: Cash&Other | G163: =custodian!D163
A164: BRZX | B164: 464286400 Equity | C164: 464286400-TRS-12/01/27-L-CANT | D164: N/A | E164: N/A | F164: ISHARES MSCI BRAZIL ETF-SWAP-CANT-L | G164: =custodian!D164 | I164: 464286400-TRS-12/01/27-L-CANT | J164: US | K164: DE | L164: OTHER | M164: SWP | V164: otherRefInst | Y164: Y | Z164: 2027-12-01 | AA164: 677270.80 | AB164: USD | AC164: -21333.21 | AD164: -21333.21 | AE164: -6.30 | AH164: Floating | AK164: 677270.80 | AL164: USD | AO164: =BDP($B164,"ISSUER") | AP164: =BDP($B164,"NAME") | AQ164: 464286400 | AR164: =BDP($B164,"ID_ISIN") | AS164: =BDP($B164,"TICKER")
A165: BRZX | B165: FGXXX US Equity | C165: FGXXX | D165: First American Government Obli | E165: =BDP($B165,"LEGAL_ENTITY_IDENTIFIER") | F165: First American Government Obligations Fund | G165: =custodian!D165 | H165: =BDP($B165,"ID_ISIN") | I165: FGXXX | J165: =BDP($B165,"CNTRY_OF_DOMICILE") | K165: STIV | L165: RF
A166: BRZX | C166: Cash&Other | G166: =custodian!D166
A167: BZZ | B167: ACHR US Equity | C167: ACHR | D167: Archer Aviation Inc | E167: =BDP($B167,"LEGAL_ENTITY_IDENTIFIER") | F167: Archer Aviation Inc | G167: =custodian!D167 | H167: =BDP($B167,"ID_ISIN") | I167: ACHR | J167: =BDP($B167,"CNTRY_OF_DOMICILE") | K167: EC | L167: CORP
A168: BZZ | B168: AIRO US Equity | C168: AIRO | D168: AIRO Group Holdings Inc | E168: =BDP($B168,"LEGAL_ENTITY_IDENTIFIER") | F168: AIRO Group Holdings Inc | G168: =custodian!D168 | H168: =BDP($B168,"ID_ISIN") | I168: AIRO | J168: =BDP($B168,"CNTRY_OF_DOMICILE") | K168: EC | L168: CORP
A169: BZZ | B169: AMPX US Equity | C169: AMPX | D169: Amprius Technologies Inc | E169: =BDP($B169,"LEGAL_ENTITY_IDENTIFIER") | F169: Amprius Technologies Inc | G169: =custodian!D169 | H169: =BDP($B169,"ID_ISIN") | I169: AMPX | J169: =BDP($B169,"CNTRY_OF_DOMICILE") | K169: EC | L169: CORP
A170: BZZ | B170: AVAV US Equity | C170: AVAV | D170: AeroVironment Inc | E170: =BDP($B170,"LEGAL_ENTITY_IDENTIFIER") | F170: AeroVironment Inc | G170: =custodian!D170 | H170: =BDP($B170,"ID_ISIN") | I170: AVAV | J170: =BDP($B170,"CNTRY_OF_DOMICILE") | K170: EC | L170: CORP
A171: BZZ | B171: AXON US Equity | C171: AXON | D171: Axon Enterprise Inc | E171: =BDP($B171,"LEGAL_ENTITY_IDENTIFIER") | F171: Axon Enterprise Inc | G171: =custodian!D171 | H171: =BDP($B171,"ID_ISIN") | I171: AXON | J171: =BDP($B171,"CNTRY_OF_DOMICILE") | K171: EC | L171: CORP
A172: BZZ | B172: BA US Equity | C172: BA | D172: Boeing Co/The | E172: =BDP($B172,"LEGAL_ENTITY_IDENTIFIER") | F172: Boeing Co/The | G172: =custodian!D172 | H172: =BDP($B172,"ID_ISIN") | I172: BA | J172: =BDP($B172,"CNTRY_OF_DOMICILE") | K172: EC | L172: CORP
A173: BZZ | B173: BETA US Equity | C173: BETA | D173: Beta Technologies Inc | E173: =BDP($B173,"LEGAL_ENTITY_IDENTIFIER") | F173: Beta Technologies Inc | G173: =custodian!D173 | H173: =BDP($B173,"ID_ISIN") | I173: BETA | J173: =BDP($B173,"CNTRY_OF_DOMICILE") | K173: EC | L173: CORP
A174: BZZ | B174: DPRO US Equity | C174: DPRO | D174: Draganfly Inc | E174: =BDP($B174,"LEGAL_ENTITY_IDENTIFIER") | F174: Draganfly Inc | G174: =custodian!D174 | H174: =BDP($B174,"ID_ISIN") | I174: DPRO | J174: =BDP($B174,"CNTRY_OF_DOMICILE") | K174: EC | L174: CORP
A175: BZZ | B175: EH US Equity | C175: EH | D175: EHang Holdings Ltd | E175: =BDP($B175,"LEGAL_ENTITY_IDENTIFIER") | F175: EHang Holdings Ltd | G175: =custodian!D175 | H175: =BDP($B175,"ID_ISIN") | I175: EH | J175: =BDP($B175,"CNTRY_OF_DOMICILE") | K175: EC | L175: CORP
A176: BZZ | B176: EVEX US Equity | C176: EVEX | D176: Eve Holding Inc | E176: =BDP($B176,"LEGAL_ENTITY_IDENTIFIER") | F176: Eve Holding Inc | G176: =custodian!D176 | H176: =BDP($B176,"ID_ISIN") | I176: EVEX | J176: =BDP($B176,"CNTRY_OF_DOMICILE") | K176: EC | L176: CORP
A177: BZZ | B177: FGXXX US Equity | C177: FGXXX | D177: First American Government Obli | E177: =BDP($B177,"LEGAL_ENTITY_IDENTIFIER") | F177: First American Government Obligations Fund | G177: =custodian!D177 | H177: =BDP($B177,"ID_ISIN") | I177: FGXXX | J177: =BDP($B177,"CNTRY_OF_DOMICILE") | K177: STIV | L177: RF
A178: BZZ | B178: HXL US Equity | C178: HXL | D178: Hexcel Corp | E178: =BDP($B178,"LEGAL_ENTITY_IDENTIFIER") | F178: Hexcel Corp | G178: =custodian!D178 | H178: =BDP($B178,"ID_ISIN") | I178: HXL | J178: =BDP($B178,"CNTRY_OF_DOMICILE") | K178: EC | L178: CORP
... A193: BZZ | B193: VTOL US Equity | C193: VTOL | D193: Bristow Group Inc | E193: =BDP($B193,"LEGAL_ENTITY_IDENTIFIER") | F193: Bristow Group Inc | G193: =custodian!D193 | H193: =BDP($B193,"ID_ISIN") | I193: VTOL | J193: =BDP($B193,"CNTRY_OF_DOMICILE") | K193: EC | L193: CORP
A194: BZZ | C194: Cash&Other | G194: =custodian!D194
A195: CAMC | B195: FGXXX US Equity | C195: FGXXX | D195: First American Government Obli | E195: =BDP($B195,"LEGAL_ENTITY_IDENTIFIER") | F195: First American Government Obligations Fund | G195: =custodian!D195 | H195: =BDP($B195,"ID_ISIN") | I195: FGXXX | J195: =BDP($B195,"CNTRY_OF_DOMICILE") | K195: STIV | L195: RF
A196: CAMC | B196: M20791105 Equity | C196: M20791105-TRS-12/01/27-L-CANT | D196: N/A | E196: N/A | F196: CAMTEK LTD.-SWAP-CANT-L | G196: =custodian!D196 | I196: M20791105-TRS-12/01/27-L-CANT | J196: US | K196: DE | L196: OTHER | M196: SWP | V196: otherRefInst | Y196: Y | Z196: 2027-12-01 | AA196: 485845.90 | AB196: USD | AC196: -7392.44 | AD196: -7392.44 | AE196: -3.04 | AH196: Floating | AK196: 485845.90 | AL196: USD | AO196: =BDP($B196,"ISSUER") | AP196: =BDP($B196,"NAME") | AQ196: M20791105 | AR196: =BDP($B196,"ID_ISIN") | AS196: =BDP($B196,"TICKER")
A197: CAMC | C197: Cash&Other | G197: =custodian!D197
A198: CARX | B198: 565394103 Equity | C198: 565394103-TRS-12/01/27-L-CANT | D198: N/A | E198: N/A | F198: MAPLEBEAR INC.-SWAP-CANT-L | G198: =custodian!D198 | I198: 565394103-TRS-12/01/27-L-CANT | J198: US | K198: DE | L198: OTHER | M198: SWP | V198: otherRefInst | Y198: Y | Z198: 2027-12-01 | AA198: 511528.20 | AB198: USD | AC198: 5432.48 | AD198: 5432.48 | AE198: 2.13 | AH198: Floating | AK198: 511528.20 | AL198: USD | AO198: =BDP($B198,"ISSUER") | AP198: =BDP($B198,"NAME") | AQ198: 565394103 | AR198: =BDP($B198,"ID_ISIN") | AS198: =BDP($B198,"TICKER")
A199: CARX | B199: FGXXX US Equity | C199: FGXXX | D199: First American Government Obli | E199: =BDP($B199,"LEGAL_ENTITY_IDENTIFIER") | F199: First American Government Obligations Fund | G199: =custodian!D199 | H199: =BDP($B199,"ID_ISIN") | I199: FGXXX | J199: =BDP($B199,"CNTRY_OF_DOMICILE") | K199: STIV | L199: RF
A200: CARX | C200: Cash&Other | G200: =custodian!D200
A201: CBIL | B201: 912797RS8 Govt | C201: 912797RS8 | D201: United States Treasury Bill 09 | E201: =BDP($B201,"LEGAL_ENTITY_IDENTIFIER") | F201: United States Treasury Bill 09/03/2026 | G201: =custodian!D201 | H201: =BDP($B201,"ID_ISIN") | J201: =BDP($B201,"CNTRY_OF_DOMICILE") | K201: DBT | L201: UST | AT201: =TEXT(BDP($B201,"MATURITY"),"yyyy-mm-dd") | AU201: =BDP($B201,"CPN_TYP") | AV201: =BDP($B201,"CPN")
A202: CBIL | B202: 912797SA6 Govt | C202: 912797SA6 | D202: United States Treasury Bill 10 | E202: =BDP($B202,"LEGAL_ENTITY_IDENTIFIER") | F202: United States Treasury Bill 10/01/2026 | G202: =custodian!D202 | H202: =BDP($B202,"ID_ISIN") | J202: =BDP($B202,"CNTRY_OF_DOMICILE") | K202: DBT | L202: UST | AT202: =TEXT(BDP($B202,"MATURITY"),"yyyy-mm-dd") | AU202: =BDP($B202,"CPN_TYP") | AV202: =BDP($B202,"CPN")
A203: CBIL | B203: 912797SK4 Govt | C203: 912797SK4 | D203: United States Treasury Bill 10 | E203: =BDP($B203,"LEGAL_ENTITY_IDENTIFIER") | F203: United States Treasury Bill 10/29/2026 | G203: =custodian!D203 | H203: =BDP($B203,"ID_ISIN") | J203: =BDP($B203,"CNTRY_OF_DOMICILE") | K203: DBT | L203: UST | AT203: =TEXT(BDP($B203,"MATURITY"),"yyyy-mm-dd") | AU203: =BDP($B203,"CPN_TYP") | AV203: =BDP($B203,"CPN")
A204: CBIL | B204: 912797SU2 Govt | C204: 912797SU2 | D204: United States Treasury Bill 11 | E204: =BDP($B204,"LEGAL_ENTITY_IDENTIFIER") | F204: United States Treasury Bill 11/27/2026 | G204: =custodian!D204 | H204: =BDP($B204,"ID_ISIN") | J204: =BDP($B204,"CNTRY_OF_DOMICILE") | K204: DBT | L204: UST | AT204: =TEXT(BDP($B204,"MATURITY"),"yyyy-mm-dd") | AU204: =BDP($B204,"CPN_TYP") | AV204: =BDP($B204,"CPN")
A205: CBIL | B205: 912797TC1 Govt | C205: 912797TC1 | D205: United States Treasury Bill 12 | E205: =BDP($B205,"LEGAL_ENTITY_IDENTIFIER") | F205: United States Treasury Bill 12/24/2026 | G205: =custodian!D205 | H205: =BDP($B205,"ID_ISIN") | J205: =BDP($B205,"CNTRY_OF_DOMICILE") | K205: DBT | L205: UST | AT205: =TEXT(BDP($B205,"MATURITY"),"yyyy-mm-dd") | AU205: =BDP($B205,"CPN_TYP") | AV205: =BDP($B205,"CPN")
A206: CBIL | B206: 912797TM9 Govt | C206: 912797TM9 | D206: United States Treasury Bill 01 | E206: =BDP($B206,"LEGAL_ENTITY_IDENTIFIER") | F206: United States Treasury Bill 01/21/2027 | G206: =custodian!D206 | H206: =BDP($B206,"ID_ISIN") | J206: =BDP($B206,"CNTRY_OF_DOMICILE") | K206: DBT | L206: UST | AT206: =TEXT(BDP($B206,"MATURITY"),"yyyy-mm-dd") | AU206: =BDP($B206,"CPN_TYP") | AV206: =BDP($B206,"CPN")
A207: CBIL | B207: 912797TV9 Govt | C207: 912797TV9 | D207: United States Treasury Bill 02 | E207: =BDP($B207,"LEGAL_ENTITY_IDENTIFIER") | F207: United States Treasury Bill 02/18/2027 | G207: =custodian!D207 | H207: =BDP($B207,"ID_ISIN") | J207: =BDP($B207,"CNTRY_OF_DOMICILE") | K207: DBT | L207: UST | AT207: =TEXT(BDP($B207,"MATURITY"),"yyyy-mm-dd") | AU207: =BDP($B207,"CPN_TYP") | AV207: =BDP($B207,"CPN")
A208: CBIL | B208: 912797UD7 Govt | C208: 912797UD7 | D208: United States Treasury Bill 03 | E208: =BDP($B208,"LEGAL_ENTITY_IDENTIFIER") | F208: United States Treasury Bill 03/18/2027 | G208: =custodian!D208 | H208: =BDP($B208,"ID_ISIN") | J208: =BDP($B208,"CNTRY_OF_DOMICILE") | K208: DBT | L208: UST | AT208: =TEXT(BDP($B208,"MATURITY"),"yyyy-mm-dd") | AU208: =BDP($B208,"CPN_TYP") | AV208: =BDP($B208,"CPN")
A209: CBIL | B209: 912797UE5 Govt | C209: 912797UE5 | D209: United States Treasury Bill 04 | E209: =BDP($B209,"LEGAL_ENTITY_IDENTIFIER") | F209: United States Treasury Bill 04/15/2027 | G209: =custodian!D209 | H209: =BDP($B209,"ID_ISIN") | J209: =BDP($B209,"CNTRY_OF_DOMICILE") | K209: DBT | L209: UST | AT209: =TEXT(BDP($B209,"MATURITY"),"yyyy-mm-dd") | AU209: =BDP($B209,"CPN_TYP") | AV209: =BDP($B209,"CPN")
A210: CBIL | B210: 912797UF2 Govt | C210: 912797UF2 | D210: United States Treasury Bill 09 | E210: =BDP($B210,"LEGAL_ENTITY_IDENTIFIER") | F210: United States Treasury Bill 09/10/2026 | G210: =custodian!D210 | H210: =BDP($B210,"ID_ISIN") | J210: =BDP($B210,"CNTRY_OF_DOMICILE") | K210: DBT | L210: UST | AT210: =TEXT(BDP($B210,"MATURITY"),"yyyy-mm-dd") | AU210: =BDP($B210,"CPN_TYP") | AV210: =BDP($B210,"CPN")
A211: CBIL | B211: 912797UG0 Govt | C211: 912797UG0 | D211: United States Treasury Bill 09 | E211: =BDP($B211,"LEGAL_ENTITY_IDENTIFIER") | F211: United States Treasury Bill 09/17/2026 | G211: =custodian!D211 | H211: =BDP($B211,"ID_ISIN") | J211: =BDP($B211,"CNTRY_OF_DOMICILE") | K211: DBT | L211: UST | AT211: =TEXT(BDP($B211,"MATURITY"),"yyyy-mm-dd") | AU211: =BDP($B211,"CPN_TYP") | AV211: =BDP($B211,"CPN")
A212: CBIL | B212: 912797UH8 Govt | C212: 912797UH8 | D212: United States Treasury Bill 09 | E212: =BDP($B212,"LEGAL_ENTITY_IDENTIFIER") | F212: United States Treasury Bill 09/24/2026 | G212: =custodian!D212 | H212: =BDP($B212,"ID_ISIN") | J212: =BDP($B212,"CNTRY_OF_DOMICILE") | K212: DBT | L212: UST | AT212: =TEXT(BDP($B212,"MATURITY"),"yyyy-mm-dd") | AU212: =BDP($B212,"CPN_TYP") | AV212: =BDP($B212,"CPN")
... A223: CBIL | B223: 912797VD6 Govt | C223: 912797VD6 | D223: United States Treasury Bill 09 | E223: =BDP($B223,"LEGAL_ENTITY_IDENTIFIER") | F223: United States Treasury Bill 09/22/2026 | G223: =custodian!D223 | H223: =BDP($B223,"ID_ISIN") | J223: =BDP($B223,"CNTRY_OF_DOMICILE") | K223: DBT | L223: UST | AT223: =TEXT(BDP($B223,"MATURITY"),"yyyy-mm-dd") | AU223: =BDP($B223,"CPN_TYP") | AV223: =BDP($B223,"CPN")
...

Sheet custodian
A1: Date | B1: Account | C1: StockTicker | D1: CUSIP | E1: SecurityName | F1: Shares | G1: Price | H1: MarketValue | I1: Weightings | J1: NetAssets | K1: SharesOutstanding | L1: CreationUnits | M1: MoneyMarketFlag
A2: 06/25/2026 | B2: GPTZ | C2: Cash&Other | D2: Cash&Other | E2: Cash & Other | F2: 125000.00000000 | G2: 1.000000 | H2: 125000.00 | I2: 100.00% | J2: 125000.00 | K2: 5000 | L2: 1.000000000000 | M2: Y
A3: 06/25/2026 | B3: ACLZ | C3: 054540208-TRS-12/01/27-L-CANT | D3: 054540208-TRS-12/01/27-L-CANT | E3: AXCELIS TECHNOLOGIES, INC.-SWAP-CANT-L | F3: 2876.00000000 | G3: 168.910000 | H3: 485785.16 | I3: 199.21% | J3: 243854.00 | K3: 10000 | L3: 2.000000000000
A4: 06/25/2026 | B4: ACLZ | C4: FGXXX | D4: 31846V336 | E4: First American Government Obligations Fund 12/01/2031 | F4: 27380.00000000 | G4: 100.000000 | H4: 27380.00 | I4: 11.23% | J4: 243854.00 | K4: 10000 | L4: 2.000000000000 | M4: Y
A5: 06/25/2026 | B5: ACLZ | C5: Cash&Other | D5: Cash&Other | E5: Cash & Other | F5: -269435.03000000 | G5: 1.000000 | H5: -269435.03 | I5: -110.49% | J5: 243854.00 | K5: 10000 | L5: 2.000000000000 | M5: Y
A6: 06/25/2026 | B6: ACMM | C6: 00108J109-TRS-07/26/27-L-MREX | D6: 00108J109-TRS-07/26/27-L-MREX | E6: ACM RESEARCH, INC.-SWAP-MREX-L | F6: 5110.00000000 | G6: 101.600000 | H6: 519176.00 | I6: 197.73% | J6: 262568.00 | K6: 10000 | L6: 2.000000000000
A7: 06/25/2026 | B7: ACMM | C7: FGXXX | D7: 31846V336 | E7: First American Government Obligations Fund 12/01/2031 | F7: 250250.00000000 | G7: 100.000000 | H7: 250250.00 | I7: 95.31% | J7: 262568.00 | K7: 10000 | L7: 2.000000000000 | M7: Y
A8: 06/25/2026 | B8: ACMM | C8: Cash&Other | D8: Cash&Other | E8: Cash & Other | F8: -506928.75000000 | G8: 1.000000 | H8: -506928.75 | I8: -193.07% | J8: 262568.00 | K8: 10000 | L8: 2.000000000000 | M8: Y
A9: 06/25/2026 | B9: AV | C9: AAL | D9: 02376R102 | E9: American Airlines Group Inc | F9: 1230.00000000 | G9: 17.440000 | H9: 21451.20 | I9: 1.51% | J9: 1423815.00 | K9: 50000 | L9: 10.000000000000
A10: 06/25/2026 | B10: AV | C10: AER | D10: N00985106 | E10: AerCap Holdings NV | F10: 200.00000000 | G10: 147.890000 | H10: 29578.00 | I10: 2.08% | J10: 1423815.00 | K10: 50000 | L10: 10.000000000000
A11: 06/25/2026 | B11: AV | C11: AIR | D11: 000361105 | E11: AAR Corp | F11: 100.00000000 | G11: 132.940000 | H11: 13294.00 | I11: 0.93% | J11: 1423815.00 | K11: 50000 | L11: 10.000000000000
A12: 06/25/2026 | B12: AV | C12: ALGT | D12: 01748X102 | E12: Allegiant Travel Co | F12: 80.00000000 | G12: 107.320000 | H12: 8585.60 | I12: 0.60% | J12: 1423815.00 | K12: 50000 | L12: 10.000000000000
A13: 06/25/2026 | B13: AV | C13: ALK | D13: 011659109 | E13: Alaska Air Group Inc | F13: 270.00000000 | G13: 51.560000 | H13: 13921.20 | I13: 0.98% | J13: 1423815.00 | K13: 50000 | L13: 10.000000000000
A14: 06/25/2026 | B14: AV | C14: ASR | D14: 40051E202 | E14: Grupo Aeroportuario del Sureste SAB de CV | F14: 60.00000000 | G14: 302.310000 | H14: 18138.60 | I14: 1.27% | J14: 1423815.00 | K14: 50000 | L14: 10.000000000000
A15: 06/25/2026 | B15: AV | C15: ATI | D15: 01741R102 | E15: ATI Inc | F15: 170.00000000 | G15: 197.590000 | H15: 33590.30 | I15: 2.36% | J15: 1423815.00 | K15: 50000 | L15: 10.000000000000
A16: 06/25/2026 | B16: AV | C16: BA | D16: 097023105 | E16: Boeing Co/The | F16: 260.00000000 | G16: 220.250000 | H16: 57265.00 | I16: 4.02% | J16: 1423815.00 | K16: 50000 | L16: 10.000000000000
A17: 06/25/2026 | B17: AV | C17: CAE | D17: 124765108 | E17: CAE Inc | F17: 460.00000000 | G17: 24.950000 | H17: 11477.00 | I17: 0.81% | J17: 1423815.00 | K17: 50000 | L17: 10.000000000000
A18: 06/25/2026 | B18: AV | C18: CPA | D18: P31076105 | E18: Copa Holdings SA | F18: 80.00000000 | G18: 156.860000 | H18: 12548.80 | I18: 0.88% | J18: 1423815.00 | K18: 50000 | L18: 10.000000000000
A19: 06/25/2026 | B19: AV | C19: CRS | D19: 144285103 | E19: Carpenter Technology Corp | F19: 60.00000000 | G19: 580.950000 | H19: 34857.00 | I19: 2.45% | J19: 1423815.00 | K19: 50000 | L19: 10.000000000000
A20: 06/25/2026 | B20: AV | C20: DAL | D20: 247361702 | E20: Delta Air Lines Inc | F20: 600.00000000 | G20: 90.650000 | H20: 54390.00 | I20: 3.82% | J20: 1423815.00 | K20: 50000 | L20: 10.000000000000
... A24: 06/25/2026 | B24: AV | C24: FDXF | D24: 314352105 | E24: Fedex Freight Holding Co Inc | F24: 75.00000000 | G24: 160.450000 | H24: 12033.75 | I24: 0.85% | J24: 1423815.00 | K24: 50000 | L24: 10.000000000000
A25: 06/25/2026 | B25: AV | C25: FGXXX | D25: 31846V336 | E25: First American Government Obligations Fund 12/01/2031 | F25: 43839.60000000 | G25: 100.000000 | H25: 43839.60 | I25: 3.08% | J25: 1423815.00 | K25: 50000 | L25: 10.000000000000 | M25: Y
A26: 06/25/2026 | B26: AV | C26: FTAI | D26: G3730V105 | E26: FTAI Aviation Ltd | F26: 130.00000000 | G26: 272.140000 | H26: 35378.20 | I26: 2.48% | J26: 1423815.00 | K26: 50000 | L26: 10.000000000000
A27: 06/25/2026 | B27: AV | C27: GD | D27: 369550108 | E27: General Dynamics Corp | F27: 200.00000000 | G27: 344.320000 | H27: 68864.00 | I27: 4.84% | J27: 1423815.00 | K27: 50000 | L27: 10.000000000000
A28: 06/25/2026 | B28: AV | C28: GE | D28: 369604301 | E28: GE AEROSPACE | F28: 440.00000000 | G28: 365.880000 | H28: 160987.20 | I28: 11.31% | J28: 1423815.00 | K28: 50000 | L28: 10.000000000000
A29: 06/25/2026 | B29: AV | C29: HEI | D29: 422806109 | E29: HEICO Corp | F29: 70.00000000 | G29: 335.300000 | H29: 23471.00 | I29: 1.65% | J29: 1423815.00 | K29: 50000 | L29: 10.000000000000
A30: 06/25/2026 | B30: AV | C30: HWM | D30: 443201108 | E30: Howmet Aerospace Inc | F30: 260.00000000 | G30: 276.060000 | H30: 71775.60 | I30: 5.04% | J30: 1423815.00 | K30: 50000 | L30: 10.000000000000
A31: 06/25/2026 | B31: AV | C31: HXL | D31: 428291108 | E31: Hexcel Corp | F31: 160.00000000 | G31: 95.480000 | H31: 15276.80 | I31: 1.07% | J31: 1423815.00 | K31: 50000 | L31: 10.000000000000
A32: 06/25/2026 | B32: AV | C32: JBLU | D32: 477143101 | E32: JetBlue Airways Corp | F32: 1220.00000000 | G32: 5.790000 | H32: 7063.80 | I32: 0.50% | J32: 1423815.00 | K32: 50000 | L32: 10.000000000000
A33: 06/25/2026 | B33: AV | C33: JOBY | D33: G65163100 | E33: Joby Aviation Inc | F33: 1470.00000000 | G33: 9.280000 | H33: 13641.60 | I33: 0.96% | J33: 1423815.00 | K33: 50000 | L33: 10.000000000000
A34: 06/25/2026 | B34: AV | C34: LMT | D34: 539830109 | E34: Lockheed Martin Corp | F34: 120.00000000 | G34: 491.640000 | H34: 58996.80 | I34: 4.14% | J34: 1423815.00 | K34: 50000 | L34: 10.000000000000
A35: 06/25/2026 | B35: AV | C35: LOAR | D35: 53947R105 | E35: Loar Holdings Inc | F35: 160.00000000 | G35: 73.800000 | H35: 11808.00 | I35: 0.83% | J35: 1423815.00 | K35: 50000 | L35: 10.000000000000
A36: 06/25/2026 | B36: AV | C36: LUV | D36: 844741108 | E36: Southwest Airlines Co | F36: 640.00000000 | G36: 50.940000 | H36: 32601.60 | I36: 2.29% | J36: 1423815.00 | K36: 50000 | L36: 10.000000000000
A37: 06/25/2026 | B37: AV | C37: MOG/A | D37: 615394202 | E37: Moog Inc | F37: 50.00000000 | G37: 404.900000 | H37: 20245.00 | I37: 1.42% | J37: 1423815.00 | K37: 50000 | L37: 10.000000000000
... A48: 06/25/2026 | B48: AV | C48: WWD | D48: 980745103 | E48: Woodward Inc | F48: 80.00000000 | G48: 432.800000 | H48: 34624.00 | I48: 2.43% | J48: 1423815.00 | K48: 50000 | L48: 10.000000000000
A49: 06/25/2026 | B49: AV | C49: Cash&Other | D49: Cash&Other | E49: Cash & Other | F49: 493.12000000 | G49: 1.000000 | H49: 493.12 | I49: 0.03% | J49: 1423815.00 | K49: 50000 | L49: 10.000000000000 | M49: Y
A50: 06/25/2026 | B50: BAY | C50: AAPL | D50: 037833100 | E50: Apple Inc | F50: 490.00000000 | G50: 293.080000 | H50: 143609.20 | I50: 7.29% | J50: 1970766.00 | K50: 70000 | L50: 14.000000000000
A51: 06/25/2026 | B51: BAY | C51: ABNB | D51: 009066101 | E51: Airbnb Inc | F51: 140.00000000 | G51: 144.400000 | H51: 20216.00 | I51: 1.03% | J51: 1970766.00 | K51: 70000 | L51: 14.000000000000
A52: 06/25/2026 | B52: BAY | C52: ADBE | D52: 00724F101 | E52: Adobe Inc | F52: 112.00000000 | G52: 196.570000 | H52: 22015.84 | I52: 1.12% | J52: 1970766.00 | K52: 70000 | L52: 14.000000000000
A53: 06/25/2026 | B53: BAY | C53: ADSK | D53: 052769106 | E53: Autodesk Inc | F53: 84.00000000 | G53: 192.610000 | H53: 16179.24 | I53: 0.82% | J53: 1970766.00 | K53: 70000 | L53: 14.000000000000
A54: 06/25/2026 | B54: BAY | C54: AFRM | D54: 00827B106 | E54: Affirm Holdings Inc | F54: 168.00000000 | G54: 77.660000 | H54: 13046.88 | I54: 0.66% | J54: 1970766.00 | K54: 70000 | L54: 14.000000000000
A55: 06/25/2026 | B55: BAY | C55: ALAB | D55: 04626A103 | E55: Astera Labs Inc | F55: 56.00000000 | G55: 399.920000 | H55: 22395.52 | I55: 1.14% | J55: 1970766.00 | K55: 70000 | L55: 14.000000000000
A56: 06/25/2026 | B56: BAY | C56: AMAT | D56: 038222105 | E56: Applied Materials Inc | F56: 98.00000000 | G56: 588.970000 | H56: 57719.06 | I56: 2.93% | J56: 1970766.00 | K56: 70000 | L56: 14.000000000000
A57: 06/25/2026 | B57: BAY | C57: AMD | D57: 007903107 | E57: Advanced Micro Devices Inc | F57: 168.00000000 | G57: 519.740000 | H57: 87316.32 | I57: 4.43% | J57: 1970766.00 | K57: 70000 | L57: 14.000000000000
A58: 06/25/2026 | B58: BAY | C58: APP | D58: 03831W108 | E58: AppLovin Corp | F58: 56.00000000 | G58: 464.960000 | H58: 26037.76 | I58: 1.32% | J58: 1970766.00 | K58: 70000 | L58: 14.000000000000
A59: 06/25/2026 | B59: BAY | C59: AVGO | D59: 11135F101 | E59: Broadcom Inc | F59: 210.00000000 | G59: 382.070000 | H59: 80234.70 | I59: 4.07% | J59: 1970766.00 | K59: 70000 | L59: 14.000000000000
A60: 06/25/2026 | B60: BAY | C60: BBIO | D60: 10806X102 | E60: Bridgebio Pharma Inc | F60: 140.00000000 | G60: 69.360000 | H60: 9710.40 | I60: 0.49% | J60: 1970766.00 | K60: 70000 | L60: 14.000000000000
A61: 06/25/2026 | B61: BAY | C61: BE | D61: 093712107 | E61: Bloom Energy Corp | F61: 84.00000000 | G61: 326.190000 | H61: 27399.96 | I61: 1.39% | J61: 1970766.00 | K61: 70000 | L61: 14.000000000000
... A69: 06/25/2026 | B69: BAY | C69: ESS | D69: 297178105 | E69: Essex Property Trust Inc | F69: 42.00000000 | G69: 281.650000 | H69: 11829.30 | I69: 0.60% | J69: 1970766.00 | K69: 70000 | L69: 14.000000000000
A70: 06/25/2026 | B70: BAY | C70: FGXXX | D70: 31846V336 | E70: First American Government Obligations Fund 12/01/2031 | F70: 27291.07000000 | G70: 100.000000 | H70: 27291.07 | I70: 1.38% | J70: 1970766.00 | K70: 70000 | L70: 14.000000000000 | M70: Y
A71: 06/25/2026 | B71: BAY | C71: FTNT | D71: 34959E109 | E71: Fortinet Inc | F71: 238.00000000 | G71: 145.280000 | H71: 34576.64 | I71: 1.75% | J71: 1970766.00 | K71: 70000 | L71: 14.000000000000
A72: 06/25/2026 | B72: BAY | C72: GILD | D72: 375558103 | E72: Gilead Sciences Inc | F72: 252.00000000 | G72: 125.160000 | H72: 31540.32 | I72: 1.60% | J72: 1970766.00 | K72: 70000 | L72: 14.000000000000
A73: 06/25/2026 | B73: BAY | C73: GOOGL | D73: 02079K305 | E73: Alphabet Inc | F73: 252.00000000 | G73: 345.290000 | H73: 87013.08 | I73: 4.42% | J73: 1970766.00 | K73: 70000 | L73: 14.000000000000
A74: 06/25/2026 | B74: BAY | C74: HOOD | D74: 770700102 | E74: Robinhood Markets Inc | F74: 252.00000000 | G74: 97.190000 | H74: 24491.88 | I74: 1.24% | J74: 1970766.00 | K74: 70000 | L74: 14.000000000000
A75: 06/25/2026 | B75: BAY | C75: HPQ | D75: 40434L105 | E75: HP Inc | F75: 602.00000000 | G75: 23.290000 | H75: 14020.58 | I75: 0.71% | J75: 1970766.00 | K75: 70000 | L75: 14.000000000000
A76: 06/25/2026 | B76: BAY | C76: INTC | D76: 458140100 | E76: Intel Corp | F76: 532.00000000 | G76: 131.650000 | H76: 70037.80 | I76: 3.55% | J76: 1970766.00 | K76: 70000 | L76: 14.000000000000
A77: 06/25/2026 | B77: BAY | C77: IOT | D77: 79589L106 | E77: Samsara Inc | F77: 336.00000000 | G77: 31.240000 | H77: 10496.64 | I77: 0.53% | J77: 1970766.00 | K77: 70000 | L77: 14.000000000000
A78: 06/25/2026 | B78: BAY | C78: ISRG | D78: 46120E602 | E78: Intuitive Surgical Inc | F78: 70.00000000 | G78: 401.830000 | H78: 28128.10 | I78: 1.43% | J78: 1970766.00 | K78: 70000 | L78: 14.000000000000
A79: 06/25/2026 | B79: BAY | C79: LITE | D79: 55024U109 | E79: Lumentum Holdings Inc | F79: 28.00000000 | G79: 842.530000 | H79: 23590.84 | I79: 1.20% | J79: 1970766.00 | K79: 70000 | L79: 14.000000000000
A80: 06/25/2026 | B80: BAY | C80: LRCX | D80: 512807306 | E80: Lam Research Corp | F80: 154.00000000 | G80: 374.800000 | H80: 57719.20 | I80: 2.93% | J80: 1970766.00 | K80: 70000 | L80: 14.000000000000
A81: 06/25/2026 | B81: BAY | C81: META | D81: 30303M102 | E81: Meta Platforms Inc | F81: 126.00000000 | G81: 557.670000 | H81: 70266.42 | I81: 3.57% | J81: 1970766.00 | K81: 70000 | L81: 14.000000000000
A82: 06/25/2026 | B82: BAY | C82: MRVL | D82: 573874104 | E82: MARVELL TECHNOLOGY INC | F82: 154.00000000 | G82: 276.700000 | H82: 42611.80 | I82: 2.16% | J82: 1970766.00 | K82: 70000 | L82: 14.000000000000
... A109: 06/25/2026 | B109: BAY | C109: ZS | D109: 98980G102 | E109: Zscaler Inc | F109: 84.00000000 | G109: 127.270000 | H109: 10690.68 | I109: 0.54% | J109: 1970766.00 | K109: 70000 | L109: 14.000000000000
A110: 06/25/2026 | B110: BAY | C110: Cash&Other | D110: Cash&Other | E110: Cash & Other | F110: 743.79000000 | G110: 1.000000 | H110: 743.79 | I110: 0.04% | J110: 1970766.00 | K110: 70000 | L110: 14.000000000000 | M110: Y
A111: 06/25/2026 | B111: BLCK | C111: APLD | D111: 038169207 | E111: Applied Digital Corp | F111: 70.00000000 | G111: 41.980000 | H111: 2938.60 | I111: 0.23% | J111: 1260375.00 | K111: 50000 | L111: 10.000000000000
A112: 06/25/2026 | B112: BLCK | C112: BKKT | D112: 05759B305 | E112: Bakkt Inc | F112: 2500.00000000 | G112: 8.290000 | H112: 20725.00 | I112: 1.64% | J112: 1260375.00 | K112: 50000 | L112: 10.000000000000
A113: 06/25/2026 | B113: BLCK | C113: BLSH | D113: G16910120 | E113: Bullish | F113: 840.00000000 | G113: 23.470000 | H113: 19714.80 | I113: 1.56% | J113: 1260375.00 | K113: 50000 | L113: 10.000000000000
A114: 06/25/2026 | B114: BLCK | C114: BMNR | D114: 09175A206 | E114: BitMine Immersion Technologies Inc | F114: 2750.00000000 | G114: 14.020000 | H114: 38555.00 | I114: 3.06% | J114: 1260375.00 | K114: 50000 | L114: 10.000000000000
A115: 06/25/2026 | B115: BLCK | C115: BTBT | D115: G1144A105 | E115: Bit Digital Inc | F115: 16180.00000000 | G115: 1.930000 | H115: 31227.40 | I115: 2.48% | J115: 1260375.00 | K115: 50000 | L115: 10.000000000000
A116: 06/25/2026 | B116: BLCK | C116: BTDR | D116: G11448100 | E116: Bitdeer Technologies Group | F116: 2830.00000000 | G116: 17.520000 | H116: 49581.60 | I116: 3.93% | J116: 1260375.00 | K116: 50000 | L116: 10.000000000000
A117: 06/25/2026 | B117: BLCK | C117: BTGO | D117: 091947101 | E117: Bitgo Holdings Inc | F117: 1940.00000000 | G117: 5.040000 | H117: 9777.60 | I117: 0.78% | J117: 1260375.00 | K117: 50000 | L117: 10.000000000000
A118: 06/25/2026 | B118: BLCK | C118: CANG | D118: G1820C102 | E118: Cango Inc/KY | F118: 48600.00000000 | G118: 0.228400 | H118: 11100.24 | I118: 0.88% | J118: 1260375.00 | K118: 50000 | L118: 10.000000000000
A119: 06/25/2026 | B119: BLCK | C119: CBOE | D119: 12503M108 | E119: Cboe Global Markets Inc | F119: 60.00000000 | G119: 249.590000 | H119: 14975.40 | I119: 1.19% | J119: 1260375.00 | K119: 50000 | L119: 10.000000000000
A120: 06/25/2026 | B120: BLCK | C120: CIFR | D120: 17253J106 | E120: Cipher Digital Inc | F120: 2760.00000000 | G120: 26.220000 | H120: 72367.20 | I120: 5.74% | J120: 1260375.00 | K120: 50000 | L120: 10.000000000000
A121: 06/25/2026 | B121: BLCK | C121: CLSK | D121: 18452B209 | E121: Cleanspark Inc | F121: 3020.00000000 | G121: 16.230000 | H121: 49014.60 | I121: 3.89% | J121: 1260375.00 | K121: 50000 | L121: 10.000000000000
A122: 06/25/2026 | B122: BLCK | C122: CME | D122: 12572Q105 | E122: CME Group Inc | F122: 220.00000000 | G122: 231.680000 | H122: 50969.60 | I122: 4.04% | J122: 1260375.00 | K122: 50000 | L122: 10.000000000000
... A128: 06/25/2026 | B128: BLCK | C128: ETOR | D128: G32089107 | E128: Etoro Group Ltd | F128: 980.00000000 | G128: 36.530000 | H128: 35799.40 | I128: 2.84% | J128: 1260375.00 | K128: 50000 | L128: 10.000000000000
A129: 06/25/2026 | B129: BLCK | C129: FGXXX | D129: 31846V336 | E129: First American Government Obligations Fund 12/01/2031 | F129: 19633.07000000 | G129: 100.000000 | H129: 19633.07 | I129: 1.56% | J129: 1260375.00 | K129: 50000 | L129: 10.000000000000 | M129: Y
A130: 06/25/2026 | B130: BLCK | C130: FIGR | D130: 349381103 | E130: Figure Technology Solutions Inc | F130: 1520.00000000 | G130: 27.400000 | H130: 41648.00 | I130: 3.30% | J130: 1260375.00 | K130: 50000 | L130: 10.000000000000
A131: 06/25/2026 | B131: BLCK | C131: FUFU | D131: G1152A104 | E131: BitFuFu Inc | F131: 8680.00000000 | G131: 1.520000 | H131: 13193.60 | I131: 1.05% | J131: 1260375.00 | K131: 50000 | L131: 10.000000000000
A132: 06/25/2026 | B132: BLCK | C132: GEMI | D132: 36866J105 | E132: Gemini Space Station Inc | F132: 5120.00000000 | G132: 4.180000 | H132: 21401.60 | I132: 1.70% | J132: 1260375.00 | K132: 50000 | L132: 10.000000000000
A133: 06/25/2026 | B133: BLCK | C133: GLXY | D133: 36317J209 | E133: Galaxy Digital Inc | F133: 1700.00000000 | G133: 28.580000 | H133: 48586.00 | I133: 3.85% | J133: 1260375.00 | K133: 50000 | L133: 10.000000000000
A134: 06/25/2026 | B134: BLCK | C134: GPGI | D134: 20459V105 | E134: GPGI Inc | F134: 2650.00000000 | G134: 14.240000 | H134: 37736.00 | I134: 2.99% | J134: 1260375.00 | K134: 50000 | L134: 10.000000000000
A135: 06/25/2026 | B135: BLCK | C135: HIVE | D135: 433921103 | E135: Hive Digital Technologies Ltd | F135: 10690.00000000 | G135: 4.140000 | H135: 44256.60 | I135: 3.51% | J135: 1260375.00 | K135: 50000 | L135: 10.000000000000
A136: 06/25/2026 | B136: BLCK | C136: HOOD | D136: 770700102 | E136: Robinhood Markets Inc | F136: 530.00000000 | G136: 97.190000 | H136: 51510.70 | I136: 4.09% | J136: 1260375.00 | K136: 50000 | L136: 10.000000000000
A137: 06/25/2026 | B137: BLCK | C137: HUT | D137: 44812J104 | E137: HUT 8 CORP | F137: 640.00000000 | G137: 116.100000 | H137: 74304.00 | I137: 5.90% | J137: 1260375.00 | K137: 50000 | L137: 10.000000000000
A138: 06/25/2026 | B138: BLCK | C138: IREN | D138: Q4982L109 | E138: IREN Ltd | F138: 1220.00000000 | G138: 50.300000 | H138: 61366.00 | I138: 4.87% | J138: 1260375.00 | K138: 50000 | L138: 10.000000000000
A139: 06/25/2026 | B139: BLCK | C139: MARA | D139: 565788106 | E139: MARA Holdings Inc | F139: 3680.00000000 | G139: 14.000000 | H139: 51520.00 | I139: 4.09% | J139: 1260375.00 | K139: 50000 | L139: 10.000000000000
A140: 06/25/2026 | B140: BLCK | C140: PYPL | D140: 70450Y103 | E140: PayPal Holdings Inc | F140: 640.00000000 | G140: 42.480000 | H140: 27187.20 | I140: 2.16% | J140: 1260375.00 | K140: 50000 | L140: 10.000000000000
A141: 06/25/2026 | B141: BLCK | C141: RIOT | D141: 767292105 | E141: Riot Platforms Inc | F141: 2560.00000000 | G141: 27.420000 | H141: 70195.20 | I141: 5.57% | J141: 1260375.00 | K141: 50000 | L141: 10.000000000000
... A144: 06/25/2026 | B144: BLCK | C144: XYZ | D144: 852234103 | E144: Block Inc | F144: 310.00000000 | G144: 75.680000 | H144: 23460.80 | I144: 1.86% | J144: 1260375.00 | K144: 50000 | L144: 10.000000000000
A145: 06/25/2026 | B145: BLCK | C145: Cash&Other | D145: Cash&Other | E145: Cash & Other | F145: 103.90000000 | G145: 1.000000 | H145: 103.90 | I145: 0.01% | J145: 1260375.00 | K145: 50000 | L145: 10.000000000000 | M145: Y
A146: 06/25/2026 | B146: BREW | C146: BRCC | D146: 05601U105 | E146: BRC Inc | F146: 67776.00000000 | G146: 1.250000 | H146: 84720.00 | I146: 5.26% | J146: 1611138.00 | K146: 60000 | L146: 12.000000000000
A147: 06/25/2026 | B147: BREW | C147: BROS | D147: 26701L100 | E147: Dutch Bros Inc | F147: 1284.00000000 | G147: 67.150000 | H147: 86220.60 | I147: 5.35% | J147: 1611138.00 | K147: 60000 | L147: 12.000000000000
A148: 06/25/2026 | B148: BREW | C148: CELH | D148: 15118V207 | E148: Celsius Holdings Inc | F148: 2136.00000000 | G148: 28.520000 | H148: 60918.72 | I148: 3.78% | J148: 1611138.00 | K148: 60000 | L148: 12.000000000000
A149: 06/25/2026 | B149: BREW | C149: DNUT | D149: 50101L106 | E149: Krispy Kreme Inc | F149: 756.00000000 | G149: 3.730000 | H149: 2819.88 | I149: 0.18% | J149: 1611138.00 | K149: 60000 | L149: 12.000000000000
A150: 06/25/2026 | B150: BREW | C150: FGXXX | D150: 31846V336 | E150: First American Government Obligations Fund 12/01/2031 | F150: 11041.90000000 | G150: 100.000000 | H150: 11041.90 | I150: 0.69% | J150: 1611138.00 | K150: 60000 | L150: 12.000000000000 | M150: Y
A151: 06/25/2026 | B151: BREW | C151: IFF | D151: 459506101 | E151: International Flavors & Fragrances Inc | F151: 960.00000000 | G151: 75.830000 | H151: 72796.80 | I151: 4.52% | J151: 1611138.00 | K151: 60000 | L151: 12.000000000000
A152: 06/25/2026 | B152: BREW | C152: INGR | D152: 457187102 | E152: Ingredion Inc | F152: 396.00000000 | G152: 98.110000 | H152: 38851.56 | I152: 2.41% | J152: 1611138.00 | K152: 60000 | L152: 12.000000000000
A153: 06/25/2026 | B153: BREW | C153: KDP | D153: 49271V100 | E153: Keurig Dr Pepper Inc | F153: 2532.00000000 | G153: 31.400000 | H153: 79504.80 | I153: 4.93% | J153: 1611138.00 | K153: 60000 | L153: 12.000000000000
...
